vault2site/main.py
vault2site/page.py
vault2site/path_check.py
vault2site/site_builder.py
vault2site/site_profile.py
vault2site/site_render.py
vault2site/extensions/__init__.py
vault2site/extensions/images.py
vault2site/extensions/internal_links.py
vault2site/extensions/sidenotes.py
vault2site-0.0.4.dist-info/METADATA
vault2site-0.0.4.dist-info/WHEEL
vault2site-0.0.4.dist-info/entry_points.txt
vault2site-0.0.4.dist-info/RECORD
