Metadata-Version: 2.1
Name: vault2site
Version: 0.0.4
Summary: Converts Obsidian.md vaults to a static site
Author: kilroyjones
Classifier: License :: OSI Approved :: MIT License
Classifier: Operating System :: OS Independent
Classifier: Programming Language :: Python :: 3
Requires-Python: >=3.8
Requires-Dist: markdown
Requires-Dist: pygments
